{"archive.md":"7a076b6d","centos-develop-env.md":"a7ca928c","git-subtree.md":"99861db1","git-ignore-exclude.md":"2c41f0f2","centos-firewall.md":"2b53e1e3","mysql-backup.md":"88d5768e","category.md":"1b267eb7","delete-with-body.md":"4e725f45","git.md":"2911823c","leovue-why.md":"0692d7c5","linux-directory.md":"b478db8e","web-internet.md":"396e6ecd","php-imagick-windows.md":"9c3c4119","frontend-tools.md":"fa190072","chrome-inspect.md":"57fadc4b","whistle-intro.md":"f4ee3f5b","mysql-on-docker.md":"0e8e97e6","git-commitlint.md":"e6a6a435","ding-cloud-push.md":"dac05af4","centos-intro.md":"3047495c","web-component.md":"cce1ee81","webpack-drop-console.md":"9e3fb8bd","kubernetes-docker-mesos.md":"f105c125","linux-make-install.md":"b1042c66","linux-shell.md":"86ea1859","kubernetes-install.md":"7fc72f5d","git-webhook.md":"8f2ad9e3","localhost-ssl-cert.md":"35af3f19","rbac.md":"41858af2","frontend-map.md":"215b2a2d","umijs-ux.md":"f2155e08","egg-oauth.md":"8e00364b","frp-ddns.md":"59badcc1","lodop.md":"f8be691c","zabbix-install.md":"5f28c446","centos-network.md":"b7e02990","vi.md":"c856cbba","centos-kvm.md":"321f4dd2","javascript-promise.md":"59d14201","centos-openvpn.md":"aec5c7d5","sql-join.md":"3442576a","oracle-plsql.md":"b7356f1c","nginx-php-fpm.md":"18bd8731","vue-props.md":"685e48a2","frp.md":"38198381","sql-antipatterns.md":"70e220b8","docker-portianer.md":"b6b6d9ad","linux-home.md":"b80bbf26","mysql-multi-version.md":"0f80a17c","javascript-mind-map.md":"0d93dbcc","leophp.md":"05d6c0c3","index.md":"e108aca7","mysql-install.md":"354a5f86","tag.md":"bb683bd6","ios-develop.md":"2e5f22a3","jekyll-intro-to-quit.md":"d496a13d","leovue-npm.md":"1ddd3178","php-lite.md":"2e4b4202","centos-info.md":"6528db92","node-on-wsl.md":"58dd9f13","webvirt-cloud.md":"549ad4ec","jquery-table.md":"9d6506e8","php-fall.md":"be49468e"}
