{"git-ignore-exclude.md":"bb83121c","linux-directory.md":"107d5a1b","archive.md":"172f51e0","git-subtree.md":"abaec0ea","linux-home.md":"2609fe3e","git.md":"3ccbc241","centos-kvm.md":"5a30d22a","javascript-mind-map.md":"a21f988f","ios-develop.md":"8e8c5b28","leophp.md":"5a33b3f0","webpack-drop-console.md":"aada6034","centos-info.md":"7de4763d","delete-with-body.md":"0e5ee0e8","jquery-table.md":"efc9c231","centos-firewall.md":"8efba071","frp-ddns.md":"8b94c127","leovue-npm.md":"05e354e7","whistle-intro.md":"a6aa9e28","jekyll-intro-to-quit.md":"7aa63776","linux-make-install.md":"0c2c6717","frontend-tools.md":"8e81be0c","leovue-why.md":"c5397ae1","sql-join.md":"a139010c","frp.md":"fe8b6d64","chrome-inspect.md":"fb6e34ac","php-fall.md":"9f45b3dd","git-webhook.md":"620c275a","zabbix-install.md":"701a87b3","git-commitlint.md":"d9c854a9","web-component.md":"943b632e","php-imagick-windows.md":"2a05262a","web-internet.md":"e7931798","index.md":"bc6457a9","vi.md":"38eea90e","webvirt-cloud.md":"660e7b4d","vue-props.md":"fb7ab3c0","category.md":"d44e8a31","mysql-multi-version.md":"4818800d","kubernetes-install.md":"6c9ddf1a","php-lite.md":"43eb6a9c","centos-network.md":"4e1a17f4","localhost-ssl-cert.md":"7a439835","tag.md":"f3f3201f","egg-oauth.md":"f1c7907e","centos-openvpn.md":"e41afb74","centos-intro.md":"0e09cf07","mysql-on-docker.md":"6c8c20b5","rbac.md":"c10fd714","javascript-async.md":"8a461c02","oracle-plsql.md":"42060997","linux-shell.md":"2db971f9","docker-portianer.md":"75811363","frontend-map.md":"17182444","mysql-backup.md":"ce27323b","nginx-php-fpm.md":"9b79c295","ding-cloud-push.md":"7bdc82e2","umijs-ux.md":"fb3d513b","centos-develop-env.md":"81293497","lodop.md":"f07bcf4f","mysql-install.md":"efcd8ac1","kubernetes-docker-mesos.md":"2d923aed","sql-antipatterns.md":"a5772fe1","node-on-wsl.md":"913c5bca"}
